School/3rd semestr/APS/cviko1/2.12/circuit.v
module circuit(input a, b, c,
                 output d, e);

  assign d = ~(a | b) | (b & c);
  assign e = (b & c) ^ c;

endmodule

School/3rd semestr/APS/cviko1/2.12/circuit_tb.v
module test();
  reg a, b, c;
  wire x, y;

  circuit circuit_XY(a, b, c, x, y); // <- zde je instance obvodu, který simulujeme.

  initial begin
    $dumpfile("test");
    $dumpvars;
    a=0;
    b=0;
    c=0;
    #160 $finish;
  end

  always #20 a = ~a;
  always #40 b = ~b;
  always #80 c = ~c;

  always @(x) #1 $display( "The value of x was changed. Time=%5d, x=%b. Inputs: a=%b, b=%b, c=%b.",$time, x,a,b,c);

endmodule

School/3rd semestr/APS/cviko1/2.12/test.vcd
$date
	Sat Oct  7 14:21:41 2023
$end
$version
	Icarus Verilog
$end
$timescale
	1s
$end
$scope module test $end
$var wire 1 ! y $end
$var wire 1 " x $end
$var reg 1 # a $end
$var reg 1 $ b $end
$var reg 1 % c $end
$scope module circuit_XY $end
$var wire 1 # a $end
$var wire 1 $ b $end
$var wire 1 % c $end
$var wire 1 " d $end
$var wire 1 ! e $end
$upscope $end
$upscope $end
$enddefinitions $end
#0
$dumpvars
0%
0$
0#
1"
0!
$end
#20
0"
1#
#40
0#
1$
#60
1#
#80
1"
1!
0#
0$
1%
#100
0"
1#
#120
1"
0!
0#
1$
#140
1#
#160
1"
0!
0#
0$
0%
